ded_sdk/__init__.py
ded_sdk/client.py
ded_sdk-0.1.0.dist-info/licenses/LICENSE
ded_sdk-0.1.0.dist-info/METADATA
ded_sdk-0.1.0.dist-info/WHEEL
ded_sdk-0.1.0.dist-info/top_level.txt
ded_sdk-0.1.0.dist-info/RECORD
