Metadata-Version: 2.4
Name: ded_sdk
Version: 0.1.0
Summary: Python SDK for Disposable Email Detection
Home-page: https://ded.gossorg.in
Author: Akshat Kotpalliwar alias IntegerAlex
Author-email: akshatkot@gmail.com
Classifier: Programming Language :: Python :: 3
Classifier: License :: OSI Approved :: MIT License
Requires-Python: >=3.6
License-File: LICENSE
Requires-Dist: requests>=2.25.1
Dynamic: author
Dynamic: author-email
Dynamic: classifier
Dynamic: description
Dynamic: description-content-type
Dynamic: home-page
Dynamic: license-file
Dynamic: requires-dist
Dynamic: requires-python
Dynamic: summary
